project_generator/cli.py
project_generator/main.py
project_generator/applications/app_service/__init__.py
project_generator/applications/settings/container.py
project_generator/domain/models/project_models.py
project_generator/domain/usecases/generation_use_case.py
project_generator/domain/usecases/restore_use_case.py
project_generator/domain/usecases/update_use_case.py
project_generator/infrastructure/generation_utils.py
project_generator/infrastructure/driven_adapters/code_injector_adapter.py
project_generator/infrastructure/driven_adapters/cookiecutter_adapter.py
project_generator/infrastructure/driven_adapters/project_analyzer_adapter.py
project_generator/infrastructure/entry_points/api_routes.py
project_generator/infrastructure/entry_points/application.py
project_generator/infrastructure/entry_points/cli/__init__.py
project_generator/infrastructure/entry_points/cli/handlers.py
project_generator/infrastructure/entry_points/cli/parsers.py
scaffold/.python-version
scaffold/cookiecutter.json
scaffold/requirements.txt
scaffold/hooks/generation_utils.py
scaffold/hooks/post_gen_project.py
scaffold/{{cookiecutter.project_slug}}/templates/agent_procode/.gitignore
scaffold/{{cookiecutter.project_slug}}/templates/agent_procode/README.md
scaffold/{{cookiecutter.project_slug}}/templates/agent_procode/main.py
scaffold/{{cookiecutter.project_slug}}/templates/agent_procode/pyproject.toml
scaffold/{{cookiecutter.project_slug}}/templates/agent_procode/application/settings/__init__.py
scaffold/{{cookiecutter.project_slug}}/templates/agent_procode/application/settings/base_settings.py
scaffold/{{cookiecutter.project_slug}}/templates/agent_procode/application/settings/container.py
scaffold/{{cookiecutter.project_slug}}/templates/agent_procode/application/settings/kafka_settings.py
scaffold/{{cookiecutter.project_slug}}/templates/agent_procode/application/settings/settings.py
scaffold/{{cookiecutter.project_slug}}/templates/agent_procode/application/settings/settings_template.txt
ca_scaffold_py-2.0.0.dist-info/METADATA
ca_scaffold_py-2.0.0.dist-info/WHEEL
ca_scaffold_py-2.0.0.dist-info/entry_points.txt
ca_scaffold_py-2.0.0.dist-info/licenses/LICENSE
ca_scaffold_py-2.0.0.dist-info/RECORD
