Metadata-Version: 2.4
Name: ca-scaffold-py
Version: 2.0.0
Summary: A Python scaffold generator for MCP (Model Context Protocol) and agent procode projects with clean architecture.
Author-email: josalfra@bancolombia.com.co
License-File: LICENSE
Requires-Python: >=3.12
Requires-Dist: cookiecutter>=2.6.0
Requires-Dist: dependency-injector>=4.48.1
Requires-Dist: fastapi>=0.116.1
Requires-Dist: pydantic>=2.11.7
Requires-Dist: python-slugify>=8.0.4
Requires-Dist: rich>=13.7.1
Requires-Dist: typer[all]>=0.12.3
Requires-Dist: uvicorn>=0.35.0
